LICENSE.md
fagus/__init__.py
fagus/fagus.py
fagus/filters.py
fagus/iterators.py
fagus/utils.py
fagus-1.1.2.dist-info/LICENSE.md
fagus-1.1.2.dist-info/METADATA
fagus-1.1.2.dist-info/WHEEL
fagus-1.1.2.dist-info/RECORD
