Metadata-Version: 2.1
Name: fagus
Version: 1.1.2
Summary: Library to easily create, edit and traverse nested objects of dicts and lists in Python
Home-page: https://github.com/treeorg/Fagus
License: ISC
Keywords: json,yaml,api,dict,list
Author: Lukas Neuenschwander
Author-email: fjellvannet@gmail.com
Maintainer: treeorg
Requires-Python: >=3.6
Classifier: License :: OSI Approved
Classifier: Programming Language :: Python :: 3
Classifier: Programming Language :: Python :: 3.6
Classifier: Programming Language :: Python :: 3.7
Classifier: Programming Language :: Python :: 3.8
Classifier: Programming Language :: Python :: 3.9
Classifier: Programming Language :: Python :: 3.10
Classifier: Programming Language :: Python :: 3.11
Requires-Dist: typing-extensions (>=3.7.4) ; python_full_version > "3.7.0" and python_version < "3.10"
Requires-Dist: typing-extensions (>=3.7.4) ; python_version >= "3.6" and python_version < "3.7"
Project-URL: Documentation, https://fagus.readthedocs.io/en/latest/
Project-URL: Repository, https://github.com/treeorg/Fagus
